list_flatten_z/__init__.py
list_flatten_z-0.5.dist-info/LICENSE.txt
list_flatten_z-0.5.dist-info/METADATA
list_flatten_z-0.5.dist-info/WHEEL
list_flatten_z-0.5.dist-info/top_level.txt
list_flatten_z-0.5.dist-info/RECORD
