Metadata-Version: 2.1
Name: list-flatten-z
Version: 0.5
Summary: A package to flatten lists using Pandas
Home-page: https://github.com/yourusername/list-flatten
Author: Neu_Basis
Author-email: streamingandflow@outlook.com
License: MIT
Classifier: License :: OSI Approved :: MIT License
Classifier: Programming Language :: Python :: 3
Classifier: Programming Language :: Python :: 3.6
Classifier: Programming Language :: Python :: 3.7
Classifier: Programming Language :: Python :: 3.8
Classifier: Programming Language :: Python :: 3.9
Classifier: Programming Language :: Python :: 3.10
License-File: LICENSE.txt
Requires-Dist: pandas
